utopia_pipeline_tools/__init__.py
utopia_pipeline_tools/analysis_tools.py
utopia_pipeline_tools/azure_blob_tools.py
utopia_pipeline_tools/classified_to_seabass.py
utopia_pipeline_tools/cnn_tools.py
utopia_pipeline_tools/ifcb_data_tools.py
utopia_pipeline_tools/pivot_ingestion_tools.py
utopia_pipeline_tools-0.3.25.dist-info/LICENSE
utopia_pipeline_tools-0.3.25.dist-info/METADATA
utopia_pipeline_tools-0.3.25.dist-info/WHEEL
utopia_pipeline_tools-0.3.25.dist-info/top_level.txt
utopia_pipeline_tools-0.3.25.dist-info/RECORD
